cointhatemij/__init__.py
cointhatemij/hatemi_j_test.py
cointhatemij-0.1.5.dist-info/licenses/LICENSE
tests/__init__.py
tests/test_comprehensive.py
tests/test_hatemi_j.py
cointhatemij-0.1.5.dist-info/METADATA
cointhatemij-0.1.5.dist-info/WHEEL
cointhatemij-0.1.5.dist-info/top_level.txt
cointhatemij-0.1.5.dist-info/RECORD
