Metadata-Version: 2.4
Name: cointhatemij
Version: 0.1.5
Summary: Hatemi-J Cointegration Test with Two Unknown Regime Shifts
Home-page: https://github.com/merwanroudane/cointhatemij
Author: Dr. Merwan Roudane
Author-email: "Dr. Merwan Roudane" <merwanroudane920@gmail.com>
License: MIT
Requires-Python: >=3.7
License-File: LICENSE
Requires-Dist: numpy>=1.19.0
Requires-Dist: scipy>=1.5.0
Dynamic: author
Dynamic: home-page
Dynamic: license-file
Dynamic: requires-python
